[
    {
        "เลขทะเบียน": "0205557034607",
        "ประกอบธุรกิจ": "จำหน่ายสินค้าพื้นเมืองและของที่ระลึก",
        "หมวดธุรกิจ": "ร้านขายปลีกผลิตภัณฑ์งานฝีมือคนไทยและของที่ระลึก",
        "สถานะ": "ยังดำเนินกิจการอยู่",
        "วันที่จดทะเบียน": "6 ตุลาคม 2557",
        "ทุนจดทะเบียน": "102,000,000 บาท",
        "ก่อตั้งโดย": "กรรมการ: นางสาววิยดา ทองจินดาวงศ์, นางสาวปนัสยา ทองจินดาวงศ์, นายธนายุทธ ทองจินดาวงศ์, นายวันจักร โชติชัยชรินทร์, นายพิธาน จิตชินะกุล, นายณรงค์ จูเจริญ",
        "ที่ตั้ง": "138/1 ถนนเพชรบุรี แขวงถนนเพชรบุรี เขตราชเทวี กรุงเทพมหานคร 10400",
        "ชื่อบริษัทภาษาอังกฤษ": "LATEX RECREATION COMPANY LIMITED",
        "ชื่อบริษัทภาษาไทย": "บริษัท เทรเชอร์ โปรดักส์ จำกัด",
        "ข้อมูลสำหรับการติดต่อ": false,
        "ที่มา": "https://www.dataforthai.com/company/0205557034607/"
    },
    {
        "เลขทะเบียน": "0835547007687",
        "ประกอบธุรกิจ": "จำหน่ายของที่ระลึก",
        "หมวดธุรกิจ": "ร้านขายปลีกผลิตภัณฑ์งานฝีมือคนไทยและของที่ระลึก",
        "สถานะ": "ยังดำเนินกิจการอยู่",
        "วันที่จดทะเบียน": "30 สิงหาคม 2547",
        "ทุนจดทะเบียน": "50,000,000 บาท",
        "ก่อตั้งโดย": "กรรมการ: นายสุระพงษ์ พิพัฒน์พัลลภ",
        "ที่ตั้ง": "888 หมู่ที่ 6 ตำบลฉลอง อำเภอเมืองภูเก็ต จ.ภูเก็ต 83130",
        "ชื่อบริษัทภาษาอังกฤษ": "ROYAL PARAGON PHUKET COMPANY LIMITED",
        "ชื่อบริษัทภาษาไทย": "บริษัท รอยัล พารากอน ภูเก็ต จำกัด",
        "ข้อมูลสำหรับการติดต่อ": false,
        "ที่มา": "https://www.dataforthai.com/company/0835547007687/"
    },
    {
        "เลขทะเบียน": "0735543001090",
        "ประกอบธุรกิจ": "ขายของที่ระลึก เครื่องจักสาน เสื้อผ้าสำเร็วรูป ของเด็กเล่น อาหารและเครื่องดื่ม",
        "หมวดธุรกิจ": "ร้านขายปลีกผลิตภัณฑ์งานฝีมือคนไทยและของที่ระลึก",
        "สถานะ": "ยังดำเนินกิจการอยู่",
        "วันที่จดทะเบียน": "5 กรกฎาคม 2543",
        "ทุนจดทะเบียน": "88,200,000 บาท",
        "ก่อตั้งโดย": "กรรมการ: นายสุพจน์ ตันติจิรสกุล, นางสาวนัสวีร์ ตันติจิรสกุล, นางสาวเมลดา ตันติจิรสกุล",
        "ที่ตั้ง": "344 ซอยจรัญสนิทวงศ์ 46 ถนนจรัญสนิทวงศ์ แขวงบางยี่ขัน เขตบางพลัด กรุงเทพมหานคร 10700",
        "ชื่อบริษัทภาษาอังกฤษ": "IYARA BIZ GROUP COMPANY LIMITED",
        "ชื่อบริษัทภาษาไทย": "บริษัท ไอยรา บิส กรุ๊ป จำกัด",
        "ข้อมูลสำหรับการติดต่อ": false,
        "ที่มา": "https://www.dataforthai.com/company/0735543001090/"
    },
    {
        "เลขทะเบียน": "0105528011115",
        "ประกอบธุรกิจ": "ขายปลีกสินค้าหัตถกรรมไทยให้บริการเช่าทรัพย์สิน",
        "หมวดธุรกิจ": "ร้านขายปลีกผลิตภัณฑ์งานฝีมือคนไทยและของที่ระลึก",
        "สถานะ": "ยังดำเนินกิจการอยู่",
        "วันที่จดทะเบียน": "27 มีนาคม 2528",
        "ทุนจดทะเบียน": "90,000,000 บาท",
        "สมัครงาน / ดูตำแหน่งงานว่าง": "ดูตำแหน่งงานจาก JOBBKK",
        "ก่อตั้งโดย": "กรรมการ: นายบรรจง สุกรีฑา, นายชาวันย์ สวัสดิ์-ชูโต, นางสุชาดา โพธิ์เจริญ, นางสาวณิชยา พหูสูตร, นายยุทธนา พูลพิพัฒน์, นางสว่าง มั่นคงเจริญ, พลตรีชยพัทธ์ หนองแสง, นางยุวดี ว่องกุศลกิจ, นายวิทยา เนติวิวัฒน์, นางยุวนิตย์ ปิสัญธนะกูล, นายสมศักดิ์ เหมทานนท์",
        "ที่ตั้ง": "555/5 ซอยสุขุมวิท 63 (เอกมัย) ถนนสุขุมวิท แขวงคลองตันเหนือ เขตวัฒนา กรุงเทพมหานคร 10110",
        "ชื่อบริษัทภาษาอังกฤษ": "NARAIPHAN CO., LTD.",
        "ชื่อบริษัทภาษาไทย": "บริษัท นารายณ์ภัณฑ์ จำกัด",
        "ข้อมูลสำหรับการติดต่อ": true,
        "ที่มา": "https://www.dataforthai.com/company/0105528011115/"
    },
    {
        "เลขทะเบียน": "0105542050327",
        "ประกอบธุรกิจ": "บริการซื้อขาย แลกเปลี่ยนเงินตราต่างประเทศธุรกิจจัดนำเที่ยว บริการทัวร์ จำหน่ายตั๋วเครื่องบิน",
        "หมวดธุรกิจ": "กิจกรรมเกี่ยวกับแลกเปลี่ยนเงินตราต่างประเทศ",
        "สถานะ": "ยังดำเนินกิจการอยู่",
        "วันที่จดทะเบียน": "14 กรกฎาคม 2542",
        "ทุนจดทะเบียน": "200,000,000 บาท",
        "เว็บไซต์": "www.superrichthailand.com",
        "ก่อตั้งโดย": "กรรมการ: นายอภิชัย สุสมาวัตนะกุล, นางศิริพร สุสมาวัตนะกุล, นายโภคิน สุสมาวัตนะกุล",
        "ที่ตั้ง": "45-45/1-2 ซอยราชดำริ 1 ถนนราชดำริ แขวงลุมพินี เขตปทุมวัน กรุงเทพมหานคร 10330",
        "ชื่อบริษัทภาษาอังกฤษ": "SUPER RICH (THAILAND) COMPANY LIMITED",
        "ชื่อบริษัทภาษาไทย": "บริษัท ซุปเปอร์ริช (ไทยแลนด์) จำกัด",
        "ข้อมูลสำหรับการติดต่อ": false,
        "ที่มา": "https://www.dataforthai.com/company/0105542050327/"
    },
    {
        "เลขทะเบียน": "0705550000401",
        "ประกอบธุรกิจ": "ให้บริการ-สถานที่ท่องเที่ยว จัดแสดงหุ่นขึ้ผึ้ง ขายปลีก-จำหน่ายอาหาร เครื่องดื่ม สินค้าพื้นเมือง",
        "หมวดธุรกิจ": "ร้านขายปลีกผลิตภัณฑ์งานฝีมือคนไทยและของที่ระลึก",
        "สถานะ": "ยังดำเนินกิจการอยู่",
        "วันที่จดทะเบียน": "13 มิถุนายน 2550",
        "ทุนจดทะเบียน": "157,050,000 บาท",
        "เว็บไซต์": "http://www.nasatta.com",
        "ก่อตั้งโดย": "กรรมการ: นายอำนวย ศิริพรเลิศ, นางนปภา ศิริพรเลิศ, นายธรรมวิทย์ ศิริพรเลิศ, นายจักรพันธ์ ศิริพรเลิศ, นายพนัส ศิริพรเลิศ",
        "ที่ตั้ง": "41/1 หมู่ที่ 3 ตำบลวังเย็น อำเภอบางแพ จ.ราชบุรี 70160",
        "ชื่อบริษัทภาษาอังกฤษ": "NASATTA COMPANY LIMITED",
        "ชื่อบริษัทภาษาไทย": "บริษัท ณสัทธา จำกัด",
        "ข้อมูลสำหรับการติดต่อ": true,
        "ที่มา": "https://www.dataforthai.com/company/0705550000401/"
    },
    {
        "เลขทะเบียน": "0105557138926",
        "ประกอบธุรกิจ": "",
        "สถานะ": "ยังดำเนินกิจการอยู่",
        "วันที่จดทะเบียน": "19 กันยายน 2557",
        "ทุนจดทะเบียน": "200,000,000 บาท",
        "เว็บไซต์": "https://www.srtforex.com/",
        "ก่อตั้งโดย": "กรรมการ: นางสาวธณัทร์ษริน สุสมาวัตนะกุล, นางสาวสิตามนินท์ สุสมาวัตนะกุล",
        "ที่ตั้ง": "183 อาคารรีเจ้นท์ เฮ้าส์ ชั้น 19 ถนนราชดำริ แขวงลุมพินี เขตปทุมวัน กรุงเทพมหานคร 10330",
        "หมวดธุรกิจ": "กิจกรรมเกี่ยวกับแลกเปลี่ยนเงินตราต่างประเทศ",
        "ชื่อบริษัทภาษาอังกฤษ": "SRT FOREX COMPANY LIMITED",
        "ชื่อบริษัทภาษาไทย": "บริษัท เอส อาร์ ที ฟอเร๊กซ์ จำกัด",
        "ข้อมูลสำหรับการติดต่อ": false,
        "ที่มา": "https://www.dataforthai.com/company/0105557138926/"
    }
]