[
    {
        "เลขทะเบียน": "0105554094031",
        "ประกอบธุรกิจ": "กิจการผลิต จัดทำ จัดสร้างรายการประเภทต่างๆ เช่น สารคดี ภาพยนตร์ โฆษณา",
        "หมวดธุรกิจ": "กิจกรรมการผลิตรายการโทรทัศน์",
        "สถานะ": "ยังดำเนินกิจการอยู่",
        "วันที่จดทะเบียน": "19 กรกฎาคม 2554",
        "ทุนจดทะเบียน": "30,000,000 บาท",
        "สมัครงาน / ดูตำแหน่งงานว่าง": "ดูตำแหน่งงานจาก JOBTOPGUN",
        "ก่อตั้งโดย": "กรรมการ: นายพลัฏฐ์ ลีกมลรัตน์, นางสาวฉงฉิน เจิ้น",
        "ที่ตั้ง": "31 ซอย12 (เกษมสมุทร 2) ถนนสายลวด ตำบลปากน้ำ อำเภอเมืองสมุทรปราการ จ.สมุทรปราการ 10270",
        "ชื่อบริษัทภาษาอังกฤษ": "PALAZZO ENGINEERING AND CONSTRUCTION CO., LTD.",
        "ชื่อบริษัทภาษาไทย": "บริษัท พาลาซโซ เอนจิเนียริ่ง แอนด์ คอนสตรัคชั่น จำกัด",
        "ข้อมูลสำหรับการติดต่อ": false,
        "ที่มา": "https://www.dataforthai.com/company/0105554094031/"
    },
    {
        "เลขทะเบียน": "0105558104804",
        "ประกอบธุรกิจ": "การผลิตรายการโทรทัศน์",
        "หมวดธุรกิจ": "กิจกรรมการผลิตรายการโทรทัศน์",
        "สถานะ": "ยังดำเนินกิจการอยู่",
        "วันที่จดทะเบียน": "26 มิถุนายน 2558",
        "ทุนจดทะเบียน": "30,000,000 บาท",
        "สมัครงาน / ดูตำแหน่งงานว่าง": "ดูตำแหน่งงานจาก JOBBKK",
        "ก่อตั้งโดย": "กรรมการ: นายบุญยงค์ ยงเจริญรัฐ",
        "ที่ตั้ง": "92/1 ถนนนราธิวาสราชนครินทร์ แขวงช่องนนทรี เขตยานนาวา กรุงเทพมหานคร 10120",
        "ชื่อบริษัทภาษาอังกฤษ": "SILK ROAD BROADCASTING TELEVISION COMPANY LIMITED",
        "ชื่อบริษัทภาษาไทย": "บริษัท ซิลค์โรด บรอดคาสติ้ง เทเลวิชั่น จำกัด",
        "ข้อมูลสำหรับการติดต่อ": false,
        "ที่มา": "https://www.dataforthai.com/company/0105558104804/"
    },
    {
        "เลขทะเบียน": "0105565126133",
        "ประกอบธุรกิจ": "",
        "สถานะ": "ยังดำเนินกิจการอยู่",
        "วันที่จดทะเบียน": "5 สิงหาคม 2565",
        "ทุนจดทะเบียน": "30,000,000 บาท",
        "ก่อตั้งโดย": "กรรมการ: นางวิชนี ศรีสวัสดิ์, นายชุมพล แจ้งไพร, นางสาวกัญธนัช กิตติถิรธรรม, นางสาวภูรดา ลิมปนาทไพศาล",
        "ที่ตั้ง": "399/93 ซอยสุขุมวิท 55 แขวงคลองตันเหนือ เขตวัฒนา กรุงเทพมหานคร 10110",
        "หมวดธุรกิจ": "กิจกรรมการผลิตรายการโทรทัศน์",
        "ชื่อบริษัทภาษาอังกฤษ": "STARSCHEF INTERNATIONAL CO., LTD.",
        "ชื่อบริษัทภาษาไทย": "บริษัท สตาร์เชฟ อินเตอร์เนชั่นแนล จำกัด",
        "ข้อมูลสำหรับการติดต่อ": false,
        "ที่มา": "https://www.dataforthai.com/company/0105565126133/"
    },
    {
        "เลขทะเบียน": "0105533003818",
        "ประกอบธุรกิจ": "ผลิตรายการ วิทยุ โทรทัศน์ ภาพนิ่ง ภาพยนตร์ วีดีทัศน์ และรายการสารคดี ซื้อขายสื่อโฆษณา ประชาสัมพันธ์ รายการวิทยุโทรทัศน์",
        "หมวดธุรกิจ": "กิจกรรมการผลิตรายการโทรทัศน์",
        "สถานะ": "ยังดำเนินกิจการอยู่",
        "วันที่จดทะเบียน": "10 มกราคม 2533",
        "ทุนจดทะเบียน": "30,000,000 บาท",
        "เว็บไซต์": "www.eingeing.com",
        "ก่อตั้งโดย": "กรรมการ: นางสาวสิทธิวดี กิตติสิทโธ",
        "ที่ตั้ง": "1213/522 ซอยลาดพร้าว 94 (ปัญจมิตร) แขวงพลับพลา เขตวังทองหลาง กรุงเทพมหานคร 10310",
        "ชื่อบริษัทภาษาอังกฤษ": "SIDTHINI CREATION COMPANY LIMITED",
        "ชื่อบริษัทภาษาไทย": "บริษัท สิทธิณี ครีเอชั่น จำกัด",
        "ข้อมูลสำหรับการติดต่อ": true,
        "ที่มา": "https://www.dataforthai.com/company/0105533003818/"
    },
    {
        "เลขทะเบียน": "0105537010533",
        "ประกอบธุรกิจ": "ผลิตรายการโทรทัศน์",
        "หมวดธุรกิจ": "กิจกรรมการผลิตรายการโทรทัศน์",
        "สถานะ": "ยังดำเนินกิจการอยู่",
        "วันที่จดทะเบียน": "25 มกราคม 2537",
        "ทุนจดทะเบียน": "30,000,000 บาท",
        "สมัครงาน / ดูตำแหน่งงานว่าง": "ดูตำแหน่งงานจาก JOBBKK",
        "ก่อตั้งโดย": "กรรมการ: นายประจักษ์ วงศ์ธิกุล, นางสาวพรรษมณฑ์ ศรีนิลสกุลภักดี, นายชายชาญ วงศ์ธิกุล",
        "ที่ตั้ง": "230/99 หมู่ที่ 12 ตำบลบางพลีใหญ่ อำเภอบางพลี จ.สมุทรปราการ 10540",
        "ชื่อบริษัทภาษาอังกฤษ": "NEVERLAND CREATION COMPANY LIMITED",
        "ชื่อบริษัทภาษาไทย": "บริษัท เนฟเวอร์แลนด์ ครีเอชั่น จำกัด",
        "ข้อมูลสำหรับการติดต่อ": false,
        "ที่มา": "https://www.dataforthai.com/company/0105537010533/"
    },
    {
        "เลขทะเบียน": "0105534025831",
        "ประกอบธุรกิจ": "ผลิตรายการโทรทัศน์",
        "หมวดธุรกิจ": "กิจกรรมการผลิตรายการโทรทัศน์",
        "สถานะ": "ยังดำเนินกิจการอยู่",
        "วันที่จดทะเบียน": "19 มีนาคม 2534",
        "ทุนจดทะเบียน": "30,000,000 บาท",
        "ก่อตั้งโดย": "กรรมการ: นางสาวพนิดา บัวบาน",
        "ที่ตั้ง": "44 ซอยนาคนิวาส 16 ถนนนาคนิวาส แขวงลาดพร้าว เขตลาดพร้าว กรุงเทพมหานคร 10230",
        "ชื่อบริษัทภาษาอังกฤษ": "PRO IMAGE CO., LTD.",
        "ชื่อบริษัทภาษาไทย": "บริษัท โปร อิมเมจ จำกัด",
        "ข้อมูลสำหรับการติดต่อ": true,
        "ที่มา": "https://www.dataforthai.com/company/0105534025831/"
    },
    {
        "เลขทะเบียน": "0105556037051",
        "ประกอบธุรกิจ": "ผลิตรายการโทรทัศน์",
        "หมวดธุรกิจ": "กิจกรรมการผลิตรายการโทรทัศน์",
        "สถานะ": "ยังดำเนินกิจการอยู่",
        "วันที่จดทะเบียน": "27 กุมภาพันธ์ 2556",
        "ทุนจดทะเบียน": "38,000,000 บาท",
        "ก่อตั้งโดย": "กรรมการ: นายพงษ์ศักดิ์ วิริยะบัณฑิตกุล",
        "ที่ตั้ง": "49 ซอยลาดพร้าว 140 ถนนลาดพร้าว แขวงคลองจั่น เขตบางกะปิ กรุงเทพมหานคร 10240",
        "ชื่อบริษัทภาษาอังกฤษ": "PEOPLE MEDIA  TV COMPANY LIMITED",
        "ชื่อบริษัทภาษาไทย": "บริษัท พีเพิลมีเดีย ทีวี จำกัด",
        "ข้อมูลสำหรับการติดต่อ": true,
        "ที่มา": "https://www.dataforthai.com/company/0105556037051/"
    },
    {
        "เลขทะเบียน": "0105548050060",
        "ประกอบธุรกิจ": "ประกอบกิจการรับจ้างผลิตและวางแผนสื่อโฆษณา",
        "หมวดธุรกิจ": "กิจกรรมการผลิตรายการโทรทัศน์",
        "สถานะ": "ยังดำเนินกิจการอยู่",
        "วันที่จดทะเบียน": "8 เมษายน 2548",
        "ทุนจดทะเบียน": "37,000,000 บาท",
        "ก่อตั้งโดย": "กรรมการ: นางสาววิมลณ์เกศ สุวพัฒน์ธุนากร",
        "ที่ตั้ง": "49 ซอยลาดพร้าว 140 ถนนลาดพร้าว แขวงคลองจั่น เขตบางกะปิ กรุงเทพมหานคร 10240",
        "ชื่อบริษัทภาษาอังกฤษ": "INTELLIGENT RESEARCH & CONSULT (THAILAND) COMPANY LIMITED",
        "ชื่อบริษัทภาษาไทย": "บริษัท อินเทลลิเจนท์ รีเสิร์ซ แอนด์ คอนเซาท์ (ประเทศไทย) จำกัด",
        "ข้อมูลสำหรับการติดต่อ": false,
        "ที่มา": "https://www.dataforthai.com/company/0105548050060/"
    },
    {
        "เลขทะเบียน": "0205552022317",
        "ประกอบธุรกิจ": "ผลิตรายการ จัดรายการ ผลิตข่าว",
        "หมวดธุรกิจ": "กิจกรรมการผลิตรายการโทรทัศน์",
        "สถานะ": "ยังดำเนินกิจการอยู่",
        "วันที่จดทะเบียน": "14 ธันวาคม 2552",
        "ทุนจดทะเบียน": "37,554,000 บาท",
        "เว็บไซต์": "www.chonburichannel.com",
        "สมัครงาน / ดูตำแหน่งงานว่าง": "ดูตำแหน่งงานจาก JOBTHAI",
        "ก่อตั้งโดย": "กรรมการ: นายดิเรก ศุภวิวรรธน์, นายพงษ์ศักดิ์ นันทวนิช, นายถนอมศักดิ์ ทรงพัฒนะโยธิน",
        "ที่ตั้ง": "70/30-32 หมู่ที่ 7 ตำบลสุรศักดิ์ อำเภอศรีราชา จ.ชลบุรี 20110",
        "ชื่อบริษัทภาษาอังกฤษ": "CABLE CHONBURI NETWORK CO.,LTD.",
        "ชื่อบริษัทภาษาไทย": "บริษัท เคเบิล ชลบุรี เน็ทเวิร์ค จำกัด",
        "ข้อมูลสำหรับการติดต่อ": false,
        "ที่มา": "https://www.dataforthai.com/company/0205552022317/"
    },
    {
        "เลขทะเบียน": "0125552009001",
        "ประกอบธุรกิจ": "ให้บริการส่งสัญญาณวิทยุ โทรทัศน์",
        "หมวดธุรกิจ": "กิจกรรมการผลิตรายการโทรทัศน์",
        "สถานะ": "ยังดำเนินกิจการอยู่",
        "วันที่จดทะเบียน": "10 กรกฎาคม 2552",
        "ทุนจดทะเบียน": "40,000,000 บาท",
        "ก่อตั้งโดย": "กรรมการ: นางเซียว หยู่ ซี, นายเว่ย เลียน-เฟง, นายธเนศ แจ้งสว่าง, นางสาววรรณิศา เอื้ออารีวรกุล, นายวัลลภัช ประทุมเมือง",
        "ที่ตั้ง": "262 ซอยรามคำแหง 2 ซอย 6 ถนนรามคำแหง 2 แขวงดอกไม้ เขตประเวศ กรุงเทพมหานคร 10250",
        "ชื่อบริษัทภาษาอังกฤษ": "FOT MSO COMPANY LIMITED",
        "ชื่อบริษัทภาษาไทย": "บริษัท เอฟโอที เอ็มเอสโอ จำกัด",
        "ข้อมูลสำหรับการติดต่อ": false,
        "ที่มา": "https://www.dataforthai.com/company/0125552009001/"
    },
    {
        "เลขทะเบียน": "0105556103126",
        "ประกอบธุรกิจ": "เกี่ยวข้องกับกิจการโทรทัศน์ในประเทศไทย ขายโฆษณา ให้บริการด้านการตลาด",
        "หมวดธุรกิจ": "กิจกรรมการผลิตรายการโทรทัศน์",
        "สถานะ": "ยังดำเนินกิจการอยู่",
        "วันที่จดทะเบียน": "28 มิถุนายน 2556",
        "ทุนจดทะเบียน": "50,000,000 บาท",
        "ก่อตั้งโดย": "กรรมการ: นายสยามรัศมิ์ เลาหสุขเกษม, นายธนกร ปุลิเวคินทร์, นางศศิกร ฉันท์เศรษฐ์, นางสาวโชนาลี เบดี คาโชเทีย, นายเคลมองต์ วาลองเตง แฟร์นองด์ ชเวบิ๊ก",
        "ที่ตั้ง": "92/5 อาคารสาธรธานี 2 ชั้น 2 ถนนสาทรเหนือ แขวงสีลม เขตบางรัก กรุงเทพมหานคร 10500",
        "ชื่อบริษัทภาษาอังกฤษ": "M TURNER COMPANY LIMITED",
        "ชื่อบริษัทภาษาไทย": "บริษัท เอ็ม เทิร์นเนอร์ จำกัด",
        "ข้อมูลสำหรับการติดต่อ": false,
        "ที่มา": "https://www.dataforthai.com/company/0105556103126/"
    },
    {
        "เลขทะเบียน": "0105548030441",
        "ประกอบธุรกิจ": "ประกอบกิจการผลิตรายการเพลงเพื่อแพร่ภาพทางโทรทัศน์",
        "หมวดธุรกิจ": "กิจกรรมการผลิตรายการโทรทัศน์",
        "สถานะ": "ยังดำเนินกิจการอยู่",
        "วันที่จดทะเบียน": "1 มีนาคม 2548",
        "ทุนจดทะเบียน": "42,700,000 บาท",
        "ก่อตั้งโดย": "กรรมการ: นายทวี คะนึง",
        "ที่ตั้ง": "599/144 ซอยโครงการเดอะคัลเลอร์ 1 โซนเค ถนนลาดปลาเค้า แขวงจรเข้บัว เขตลาดพร้าว กรุงเทพมหานคร 10230",
        "ชื่อบริษัทภาษาอังกฤษ": "VERY INCORPORRATION  COMPANY LIMITED",
        "ชื่อบริษัทภาษาไทย": "บริษัท บีวี รีเทลส์ จำกัด",
        "ข้อมูลสำหรับการติดต่อ": false,
        "ที่มา": "https://www.dataforthai.com/company/0105548030441/"
    },
    {
        "เลขทะเบียน": "0105545031234",
        "ประกอบธุรกิจ": "ประกอบกิจการรับผลิตรายการโทรทัศน์ วีดีโอเทป ภาพพยนตร์",
        "หมวดธุรกิจ": "กิจกรรมการผลิตรายการโทรทัศน์",
        "สถานะ": "ยังดำเนินกิจการอยู่",
        "วันที่จดทะเบียน": "20 มีนาคม 2545",
        "ทุนจดทะเบียน": "45,000,000 บาท",
        "เว็บไซต์": "http://www.tvburabha.com",
        "ก่อตั้งโดย": "กรรมการ: นายกฤษณพล พงศ์ธนาวรานนท์, นายอนุพันธ์ กิจนิจชีวะ, นางสาวอติยา อาวัชนาการ, นางสาวเดือนเด่น รัตตะมาน, นางอัจฉรา รัตนพันธุ์ศรี",
        "ที่ตั้ง": "246/8 ซอยโยธินพัฒนา แขวงคลองจั่น เขตบางกะปิ กรุงเทพมหานคร 10240",
        "ชื่อบริษัทภาษาอังกฤษ": "TV.BURABHA CO.,LTD.",
        "ชื่อบริษัทภาษาไทย": "บริษัท ทีวีบูรพา จำกัด",
        "ข้อมูลสำหรับการติดต่อ": true,
        "ที่มา": "https://www.dataforthai.com/company/0105545031234/"
    },
    {
        "เลขทะเบียน": "0105552127551",
        "ประกอบธุรกิจ": "บริษัทประกอบธุรกิจเปิดช่องสถานีโทรทัศน์ เคเบิ้ลทีวี จัดทำรายการทีวีทุกประเภท",
        "หมวดธุรกิจ": "กิจกรรมการผลิตรายการโทรทัศน์",
        "สถานะ": "ยังดำเนินกิจการอยู่",
        "วันที่จดทะเบียน": "24 พฤศจิกายน 2552",
        "ทุนจดทะเบียน": "45,000,000 บาท",
        "ก่อตั้งโดย": "กรรมการ: นายวิชญ์ ไวฑูรเกียรติ",
        "ที่ตั้ง": "333 หมู่ที่ 7 ตำบลหลักหก อำเภอเมืองปทุมธานี จ.ปทุมธานี 12000",
        "ชื่อบริษัทภาษาอังกฤษ": "TRAVEL CHANNEL CORPORATION CO.,LTD.",
        "ชื่อบริษัทภาษาไทย": "บริษัท แทรเวล แชนแนล คอร์ปอเรชั่น จำกัด",
        "ข้อมูลสำหรับการติดต่อ": false,
        "ที่มา": "https://www.dataforthai.com/company/0105552127551/"
    },
    {
        "เลขทะเบียน": "0105538048194",
        "ประกอบธุรกิจ": "ให้บริการเคเบิลทีวี",
        "หมวดธุรกิจ": "การจัดพิมพ์จำหน่ายหรือเผยแพร่โบรชัวร์ใบปลิวและสิ่งพิมพ์อื่นๆที่คล้ายกันลงบนสื่อต่างๆ (ยกเว้นทางออนไลน์)",
        "สถานะ": "ยังดำเนินกิจการอยู่",
        "วันที่จดทะเบียน": "19 เมษายน 2538",
        "ทุนจดทะเบียน": "46,000,000 บาท",
        "เว็บไซต์": "http://www.newfibercable.com/16897237/%e0%b8%aa%e0%b8%b4%e0%b8%99%e0%b8%84%e0%b9%89%e0%b8%b2-%e0%b8%9a%e0%b8%a3%e0%b8%b4%e0%b8%81%e0%b8%b2%e0%b8%a3",
        "สมัครงาน / ดูตำแหน่งงานว่าง": "ดูตำแหน่งงานจาก JOBTHAI",
        "ก่อตั้งโดย": "กรรมการ: นายเกษม อินทร์แก้ว, นางสาวมาลินี โตการค้า, นายมานะพร ปลอดภัย",
        "ที่ตั้ง": "23/403 ซอย68 ถนนโชคชัย4 แขวงลาดพร้าว เขตลาดพร้าว กรุงเทพมหานคร 10230",
        "ชื่อบริษัทภาษาอังกฤษ": "HI-TECH CABLE TELEVISION CO., LTD.",
        "ชื่อบริษัทภาษาไทย": "บริษัท ไฮ-เทค เคเบิล เทเลวิชั่น จำกัด",
        "ข้อมูลสำหรับการติดต่อ": true,
        "ที่มา": "https://www.dataforthai.com/company/0105538048194/"
    },
    {
        "เลขทะเบียน": "0105546014287",
        "ประกอบธุรกิจ": "",
        "สถานะ": "ยังดำเนินกิจการอยู่",
        "วันที่จดทะเบียน": "3 กุมภาพันธ์ 2546",
        "ทุนจดทะเบียน": "48,000,000 บาท",
        "เว็บไซต์": "http://www.belinkmedia.com",
        "ก่อตั้งโดย": "กรรมการ: นายกฤษณะ ถนอมทรัพย์, นางสาวปรางทิพย์ อรรถพรรณ, นายธนชัย ถนอมทรัพย์, นางสาววรรณวิไล โพธาเภรี, นายกิติพัฒก์ เนื่องจำนงค์, นางสาวพิมพ์วดี มนต์อภิวันท์, นายธนการ ดำรงรัตน์",
        "ที่ตั้ง": "2044/28-33 ชั้นที่ 4-6 ถนนเพชรบุรีตัดใหม่ แขวงบางกะปิ เขตห้วยขวาง กรุงเทพมหานคร 10310",
        "หมวดธุรกิจ": "กิจกรรมการผลิตรายการโทรทัศน์",
        "ชื่อบริษัทภาษาอังกฤษ": "BELINK MEDIA CO.,LTD.",
        "ชื่อบริษัทภาษาไทย": "บริษัท บีลิงค์ มีเดีย จำกัด",
        "ข้อมูลสำหรับการติดต่อ": false,
        "ที่มา": "https://www.dataforthai.com/company/0105546014287/"
    },
    {
        "ประกอบธุรกิจ": "ประกอบธุรกิจเกี่ยวกับกัญชาเพื่อประโยชน์ทางการแพทย์",
        "สถานะ": "ยังดำเนินกิจการอยู่",
        "จดทะเบียน": "2 สิงหาคม 2538",
        "ทุนจดทะเบียน": "150,000,000 บาท",
        "ก่อตั้งโดย": "กรรมการ: นายกิจชาญพิชญ์ สุกังวานวิทย์, นายถิรพงศ์ คำเรืองฤทธิ์, นายเจมส์ แอนดริว มอร์",
        "ที่ตั้ง": "2445/19 อาคารธารารมณ์ บิสซิเนส ทาวเวอร์ ชั้นที่ 14 ถนนเพชรบุรีตัดใหม่ แขวงบางกะปิ เขตห้วยขวาง กรุงเทพมหานคร 10310",
        "หมวดธุรกิจ": "การขายส่งสินค้าทางเภสัชภัณฑ์และทางการแพทย์",
        "ชื่อบริษัทภาษาอังกฤษ": "WAVE  WELLBEING CO., LTD.",
        "ชื่อบริษัทภาษาไทย": "บริษัท เวฟ เวลบีอิ้ง จำกัด",
        "ข้อมูลสำหรับการติดต่อ": true,
        "ที่มา": "https://www.dataforthai.com/company/0105538091430/",
        "เลขทะเบียน": "0105538091430"
    },
    {
        "เลขทะเบียน": "0105562129867",
        "ประกอบธุรกิจ": "การผลิตรายการ",
        "หมวดธุรกิจ": "กิจกรรมการผลิตรายการโทรทัศน์",
        "สถานะ": "ยังดำเนินกิจการอยู่",
        "วันที่จดทะเบียน": "26 กรกฎาคม 2562",
        "ทุนจดทะเบียน": "94,000,000 บาท",
        "สมัครงาน / ดูตำแหน่งงานว่าง": "ดูตำแหน่งงานจาก JOBTHAI",
        "ก่อตั้งโดย": "กรรมการ: นายศตวรรษ อินทรายุธ",
        "ที่ตั้ง": "333/4 หมู่บ้าน รัชดานิเวศน์ ซอย 19 ถนนประชาอุทิศ แขวงสามเสนนอก เขตห้วยขวาง กรุงเทพมหานคร 10310",
        "ชื่อบริษัทภาษาอังกฤษ": "KING OF GAMERS CLUB CO., LTD.",
        "ชื่อบริษัทภาษาไทย": "บริษัท คิง ออฟ เกมเมอร์ คลับ จำกัด",
        "ข้อมูลสำหรับการติดต่อ": false,
        "ที่มา": "https://www.dataforthai.com/company/0105562129867/"
    },
    {
        "เลขทะเบียน": "0105564153277",
        "ประกอบธุรกิจ": "",
        "สถานะ": "ยังดำเนินกิจการอยู่",
        "วันที่จดทะเบียน": "25 ตุลาคม 2564",
        "ทุนจดทะเบียน": "55,000,000 บาท",
        "ก่อตั้งโดย": "กรรมการ: นายบวรรัตน์ กาญจนรัตน์, นางสาวอุมาพร อรรคทัย, นายอิทธิศักดิ์ ดาราฉาย, นายจริงใจ เชาวน์ชาติ",
        "ที่ตั้ง": "118/1 ถนนพระราม 6 แขวงพญาไท เขตพญาไท กรุงเทพมหานคร 10400",
        "หมวดธุรกิจ": "กิจกรรมการผลิตรายการโทรทัศน์",
        "ชื่อบริษัทภาษาอังกฤษ": "MITI ART MEDIA CO., LTD.",
        "ชื่อบริษัทภาษาไทย": "บริษัท มิติ อาทส์ มีเดีย จำกัด",
        "ข้อมูลสำหรับการติดต่อ": false,
        "ที่มา": "https://www.dataforthai.com/company/0105564153277/"
    },
    {
        "เลขทะเบียน": "0105528014319",
        "ประกอบธุรกิจ": "ประกอบกิจการรับจ้างจัดรายการทางโทรทัศน์ รับอัดวีดีโอ เพื่อความบันเทิง สารคดี วิชาการ รวมทั้งจัดรายกา",
        "หมวดธุรกิจ": "กิจกรรมการผลิตรายการโทรทัศน์",
        "สถานะ": "แปรสภาพ",
        "วันที่จดทะเบียน": "22 เมษายน 2528",
        "ทุนจดทะเบียน": "60,000,000 บาท",
        "ที่ตั้ง": "2991/29-30 ถนนลาดพร้าว แขวงคลองจั่น เขตบางกะปิ กรุงเทพมหานคร 10240",
        "ชื่อบริษัทภาษาอังกฤษ": "MEDIA OFF MEDIA COMPANY LIMITED",
        "ชื่อบริษัทภาษาไทย": "บริษัท มีเดีย ออฟ มีเดียส์ จำกัด",
        "ข้อมูลสำหรับการติดต่อ": false,
        "ที่มา": "https://www.dataforthai.com/company/0105528014319/"
    },
    {
        "เลขทะเบียน": "0105562018861",
        "ประกอบธุรกิจ": "การผลิตรายการโทรทัศน์",
        "หมวดธุรกิจ": "กิจกรรมการผลิตรายการโทรทัศน์",
        "สถานะ": "ยังดำเนินกิจการอยู่",
        "วันที่จดทะเบียน": "29 มกราคม 2562",
        "ทุนจดทะเบียน": "60,000,000 บาท",
        "ก่อตั้งโดย": "กรรมการ: นางสาวทรงสุดา พาณิชย์",
        "ที่ตั้ง": "87 อาคารเอ็มไทย ออลซีซั่นเพลส ชั้นที่ 10 ห้องเลขที่ 5 ถนนวิทยุ แขวงลุมพินี เขตปทุมวัน กรุงเทพมหานคร 10330",
        "ชื่อบริษัทภาษาอังกฤษ": "MEDIA TANK COMPANY LIMITED",
        "ชื่อบริษัทภาษาไทย": "บริษัท มีเดีย แท็งค์ จำกัด",
        "ข้อมูลสำหรับการติดต่อ": false,
        "ที่มา": "https://www.dataforthai.com/company/0105562018861/"
    },
    {
        "เลขทะเบียน": "0105531021312",
        "ประกอบธุรกิจ": "ประกอบกิจการให้บริการจัดรายการ ผลิตรายการและออกอากาศทางสื่อ",
        "หมวดธุรกิจ": "กิจกรรมการผลิตรายการโทรทัศน์",
        "สถานะ": "ยังดำเนินกิจการอยู่",
        "วันที่จดทะเบียน": "25 มีนาคม 2531",
        "ทุนจดทะเบียน": "60,000,000 บาท",
        "เว็บไซต์": "www.nextsteptv.com",
        "ก่อตั้งโดย": "กรรมการ: นายอมรภัทร ชมรัตน์, นายไพศาล จารุรัตนรงค์, นางสาคร ชมรัตน์",
        "ที่ตั้ง": "319 ซอยรามคำแหง 60 (สวนสน) แขวงหัวหมาก เขตบางกะปิ กรุงเทพมหานคร",
        "ชื่อบริษัทภาษาอังกฤษ": "NEXT STEP COMPANY LIMITED",
        "ชื่อบริษัทภาษาไทย": "บริษัท เนกซ์ สเตป จำกัด",
        "ข้อมูลสำหรับการติดต่อ": false,
        "ที่มา": "https://www.dataforthai.com/company/0105531021312/"
    },
    {
        "เลขทะเบียน": "0105534112432",
        "ประกอบธุรกิจ": "รับจ้างผลิตและผลิตรายการโทรทัศน์เพื่อจำหน่าย",
        "หมวดธุรกิจ": "กิจกรรมการผลิตรายการโทรทัศน์",
        "สถานะ": "ยังดำเนินกิจการอยู่",
        "วันที่จดทะเบียน": "27 พฤศจิกายน 2534",
        "ทุนจดทะเบียน": "60,000,000 บาท",
        "ก่อตั้งโดย": "กรรมการ: นางสาวบุษบา ดาวเรือง, นายกิตติศักดิ์ ช่วงอรุณ, นายสันติสุข จงมั่นคง",
        "ที่ตั้ง": "50 ถนนสุขุมวิท 21 (อโศก) แขวงคลองเตยเหนือ เขตวัฒนา กรุงเทพมหานคร 10110",
        "ชื่อบริษัทภาษาอังกฤษ": "EXACT COMPANY LIMITED",
        "ชื่อบริษัทภาษาไทย": "บริษัท เอ็กแซ็กท์ จำกัด",
        "ข้อมูลสำหรับการติดต่อ": false,
        "ที่มา": "https://www.dataforthai.com/company/0105534112432/"
    },
    {
        "เลขทะเบียน": "0105554142230",
        "ประกอบธุรกิจ": "ประกอบกิจการ ผลิตและบริการสถานีโทรทัศน์ดาวเทียม ภาพยนตร์สารคดี ผลิตนิตยสาร วารสารและสื่อโฆษณาอื่นทุกชนิด",
        "หมวดธุรกิจ": "กิจกรรมการผลิตรายการโทรทัศน์",
        "สถานะ": "ยังดำเนินกิจการอยู่",
        "วันที่จดทะเบียน": "1 พฤศจิกายน 2554",
        "ทุนจดทะเบียน": "60,000,000 บาท",
        "ก่อตั้งโดย": "กรรมการ: นายธวัช ชาติวรเดช, นางกานดา เม่นวิจิตร, นายคัมภีร์ ภาคสุวรรณ์, นายศักดิ์ชัย พฤฒิภัค, นางสาววราภรณ์ ชูพระคุณ",
        "ที่ตั้ง": "460,462 ถนนพระรามที่ 3 แขวงบางโคล่ เขตบางคอแหลม กรุงเทพมหานคร 10120",
        "ชื่อบริษัทภาษาอังกฤษ": "THAIPHIROM STAR CO.,LTD.",
        "ชื่อบริษัทภาษาไทย": "บริษัท ไทยภิรมย์สตาร์ จำกัด",
        "ข้อมูลสำหรับการติดต่อ": false,
        "ที่มา": "https://www.dataforthai.com/company/0105554142230/"
    },
    {
        "เลขทะเบียน": "0107547000516",
        "ประกอบธุรกิจ": "",
        "สถานะ": "ยังดำเนินกิจการอยู่",
        "วันที่จดทะเบียน": "19 พฤษภาคม 2547",
        "ทุนจดทะเบียน": "67,787,266 บาท",
        "ก่อตั้งโดย": "กรรมการ: พลเอกไพบูลย์ เอมพันธุ์, พลโทเอนก สาตราวุธ, นางนภา จามิกรณ์, นางสาวกรนันท์ สุคนธ์ฤทธิกร, นางสาววินิตา จามิกรณ์, นายไพบูลย์ ประกอบการดี",
        "ที่ตั้ง": "50/9 ซอยแสงเงิน ถนนสุขุมวิท แขวงคลองตันเหนือ เขตวัฒนา กรุงเทพมหานคร 10110",
        "หมวดธุรกิจ": "กิจกรรมการผลิตรายการโทรทัศน์",
        "ชื่อบริษัทภาษาอังกฤษ": "B.H.I. HOLDING PUBLIC COMPANY LIMITED",
        "ชื่อบริษัทภาษาไทย": "บริษัท บี.เอช.ไอ.โฮลดิ้ง จำกัด (มหาชน)",
        "ข้อมูลสำหรับการติดต่อ": false,
        "ที่มา": "https://www.dataforthai.com/company/0107547000516/"
    },
    {
        "เลขทะเบียน": "0105540102796",
        "ประกอบธุรกิจ": "ผลิตรายการโทรทัศน์",
        "หมวดธุรกิจ": "กิจกรรมการผลิตรายการโทรทัศน์",
        "สถานะ": "เลิก",
        "วันที่จดทะเบียน": "18 ธันวาคม 2540",
        "วันที่เลิก": "10 เมษายน 2566",
        "ทุนจดทะเบียน": "71,700,000 บาท",
        "ที่ตั้ง": "1213/411 ซอยลาดพร้าว 94 ถนนศรีวรา แขวงพลับพลา เขตวังทองหลาง กรุงเทพมหานคร 10310",
        "ชื่อบริษัทภาษาอังกฤษ": "RERNGRIT CHAIMET COMPANY LIMITED",
        "ชื่อบริษัทภาษาไทย": "บริษัท เริงฤทธิ์ ชัยเมธ จำกัด",
        "ข้อมูลสำหรับการติดต่อ": false,
        "ที่มา": "https://www.dataforthai.com/company/0105540102796/"
    },
    {
        "เลขทะเบียน": "0105547126861",
        "ประกอบธุรกิจ": "ผลิตรายการโทรทัศน์เพื่อออกอากาศ",
        "หมวดธุรกิจ": "กิจกรรมการผลิตรายการโทรทัศน์",
        "สถานะ": "ยังดำเนินกิจการอยู่",
        "วันที่จดทะเบียน": "16 กันยายน 2547",
        "ทุนจดทะเบียน": "80,000,000 บาท",
        "เว็บไซต์": "https://m.youtube.com/user/mushroomtelevision",
        "ก่อตั้งโดย": "กรรมการ: นายสุทธิเกียรติ จิราธิวัฒน์, นายวรชัย พิจารณ์จิตร, นายเอกฤทธิ์ บุญปิติ, นายธีระเกียรติ จิราธิวัฒน์, นายอรรฆรัตน์ นิติพน, หม่อมหลวงพอยศ กัลยาณะวงศ์, นายเกรียงไกร กาญจนะโภคิน, นายพัฒนพงศ์ รานุรักษ์, นายแดน ชินสุภัคกุล",
        "ที่ตั้ง": "23/104 อาร์.ซี.เอ. บล็อก จี ซอยศูนย์วิจัย ถนนพระราม9 แขวงบางกะปิ เขตห้วยขวาง กรุงเทพมหานคร 10310",
        "ชื่อบริษัทภาษาอังกฤษ": "MUSHROOM GROUP COMPANY LIMITED",
        "ชื่อบริษัทภาษาไทย": "บริษัท มัชรูม กรุ๊ป จำกัด",
        "ข้อมูลสำหรับการติดต่อ": true,
        "ที่มา": "https://www.dataforthai.com/company/0105547126861/"
    },
    {
        "เลขทะเบียน": "0105532114217",
        "ประกอบธุรกิจ": "ผลิตรายการโทรทัศน์ละคร ข่าวสารคดี แถบบันทึกภาพและจำหน่ายสื่อโฆษณา",
        "หมวดธุรกิจ": "กิจกรรมการผลิตรายการโทรทัศน์",
        "สถานะ": "ยังดำเนินกิจการอยู่",
        "วันที่จดทะเบียน": "27 พฤศจิกายน 2532",
        "ทุนจดทะเบียน": "90,000,000 บาท",
        "สมัครงาน / ดูตำแหน่งงานว่าง": "ดูตำแหน่งงานจาก JOBTH",
        "ก่อตั้งโดย": "กรรมการ: นางสาวอรุโณชา ภาณุพันธุ์, นายอรรควุฒิ สุวรรณประกร",
        "ที่ตั้ง": "55 อาคารเดลต้า เฮ้าส์ ชั้น 1 ถนนเทียมร่วมมิตร แขวงห้วยขวาง เขตห้วยขวาง กรุงเทพมหานคร 10310",
        "ชื่อบริษัทภาษาอังกฤษ": "BROADCAST THAI-TELEVISION COMPANY LIMITED",
        "ชื่อบริษัทภาษาไทย": "บริษัท บรอดคาซท์ ไทย เทเลวิชั่น จำกัด",
        "ข้อมูลสำหรับการติดต่อ": false,
        "ที่มา": "https://www.dataforthai.com/company/0105532114217/"
    },
    {
        "เลขทะเบียน": "0105538034037",
        "ประกอบธุรกิจ": "บริหารคลื่นวิทยุ",
        "หมวดธุรกิจ": "กิจกรรมการผลิตรายการโทรทัศน์",
        "สถานะ": "ยังดำเนินกิจการอยู่",
        "วันที่จดทะเบียน": "16 มีนาคม 2538",
        "ทุนจดทะเบียน": "90,000,000 บาท",
        "ก่อตั้งโดย": "กรรมการ: นายบุญชัย เบญจรงคกุล, นายสมชาย เบญจรงคกุล, นายวิชัย เบญจรงคกุล, นางนฤมล ล้อมทอง",
        "ที่ตั้ง": "287/195 ซอยรามคำแหง 21 (นวศรี) ถนนประดิษฐ์มนูธรรม แขวงพลับพลา เขตวังทองหลาง กรุงเทพมหานคร 10310",
        "ชื่อบริษัทภาษาอังกฤษ": "I.N.N.RUAM DUAY CHUAY KAN COMPANY LIMITED",
        "ชื่อบริษัทภาษาไทย": "บริษัท ไอ.เอ็น.เอ็น.ร่วมด้วยช่วยกัน จำกัด",
        "ข้อมูลสำหรับการติดต่อ": false,
        "ที่มา": "https://www.dataforthai.com/company/0105538034037/"
    },
    {
        "เลขทะเบียน": "0125563034304",
        "ประกอบธุรกิจ": "โฆษณาประชาสัมพันธ์",
        "หมวดธุรกิจ": "กิจกรรมของบริษัทโฆษณา",
        "สถานะ": "ยังดำเนินกิจการอยู่",
        "วันที่จดทะเบียน": "18 ธันวาคม 2563",
        "ทุนจดทะเบียน": "100,000,000 บาท",
        "เว็บไซต์": "www.topnews.co.th",
        "ก่อตั้งโดย": "กรรมการ: นายฉัตรชัย ภู่โคกหวาย, นางลักขณา รัตน์วงศ์สกุล, นายตระกูล วินิจนัยภาค, นายเอกชัย ชัยเชิดชูกิจ, นายชยธร ธนวรเจต, นายเอกพันธุ์ แป้นไทย, นายพงษ์ศักดิ์ ชมสุวรรณ, นางสาวสุธิดา สาริกุล",
        "ที่ตั้ง": "333 หมู่ที่ 4 ตำบลบางโฉลง อำเภอบางพลี จ.สมุทรปราการ 10540",
        "ชื่อบริษัทภาษาอังกฤษ": "TOP NEWS DIGITAL MEDIA CO., LTD.",
        "ชื่อบริษัทภาษาไทย": "บริษัท ท็อปนิวส์ ดิจิตัล มีเดีย จำกัด",
        "ข้อมูลสำหรับการติดต่อ": true,
        "ที่มา": "https://www.dataforthai.com/company/0125563034304/"
    },
    {
        "เลขทะเบียน": "0105560184241",
        "ประกอบธุรกิจ": "การผลิต รับจ้างผลิตและให้คำปรึกษาสำหรับการผลิตสื่อทุกชนิต รับจ้างโฆษณา การซื้อ จัดหา ให้เช่า และถือกรรมสิทธิ์ในทรัพย์สินต่างๆ เพื่อแสวงหารายได้จากการถือกรรมสิทธิ์นั้นๆ",
        "หมวดธุรกิจ": "กิจกรรมการผลิตรายการโทรทัศน์",
        "สถานะ": "ยังดำเนินกิจการอยู่",
        "วันที่จดทะเบียน": "2 พฤศจิกายน 2560",
        "ทุนจดทะเบียน": "100,000,000 บาท",
        "ก่อตั้งโดย": "กรรมการ: นายนรรัตน์ ลิ่มนรรัตน์, นายกำพล ปุญโสณี, นายศิริ บุญพิทักษ์เกศ, นายอมร อึ้งสกุลปรีชา",
        "ที่ตั้ง": "378 ถนนชัยพฤกษ์ แขวงตลิ่งชัน เขตตลิ่งชัน กรุงเทพมหานคร 10170",
        "ชื่อบริษัทภาษาอังกฤษ": "AMARIN OMNIVERSE COMPANY LIMITED",
        "ชื่อบริษัทภาษาไทย": "บริษัท อมรินทร์ ออมนิเวิร์ส จำกัด",
        "ข้อมูลสำหรับการติดต่อ": true,
        "ที่มา": "https://www.dataforthai.com/company/0105560184241/"
    },
    {
        "เลขทะเบียน": "0105528019566",
        "ประกอบธุรกิจ": "ประกอบธุรกิจเกี่ยวกับคาร์บอนเครดิตรและให้บริการแนะนำและปรึกษา",
        "หมวดธุรกิจ": "บริการเกี่ยวกับสิทธิพิเศษอื่น ๆ",
        "สถานะ": "ยังดำเนินกิจการอยู่",
        "วันที่จดทะเบียน": "5 มิถุนายน 2528",
        "ทุนจดทะเบียน": "500,000,000 บาท",
        "ก่อตั้งโดย": "กรรมการ: นายกิจชาญพิชญ์ สุกังวานวิทย์, นายถิรพงศ์ คำเรืองฤทธิ์",
        "ที่ตั้ง": "2445/19 อาคารธารารมณ์ บิสซิเนส ทาวเวอร์ ชั้น 14 ถนนเพชรบุรีตัดใหม่ แขวงบางกะปิ เขตห้วยขวาง กรุงเทพมหานคร 10310",
        "ชื่อบริษัทภาษาอังกฤษ": "WAVE BCG CO., LTD.",
        "ชื่อบริษัทภาษาไทย": "บริษัท เวฟ บีซีจี จำกัด",
        "ข้อมูลสำหรับการติดต่อ": false,
        "ที่มา": "https://www.dataforthai.com/company/0105528019566/"
    },
    {
        "เลขทะเบียน": "0105545029604",
        "ประกอบธุรกิจ": "ให้บริการข้อมูลและสาระบันเทิงผ่านช่องทางต่างๆ",
        "หมวดธุรกิจ": "กิจกรรมการผลิตรายการโทรทัศน์",
        "สถานะ": "แปรสภาพ เป็น บริษัท โมโน เน็กซ์ จำกัด (มหาชน)",
        "วันที่จดทะเบียน": "15 มีนาคม 2545",
        "ทุนจดทะเบียน": "100,000,000 บาท",
        "เว็บไซต์": "https://www.mono.co.th/th/",
        "ที่ตั้ง": "200 อาคารจัสมิน อินเตอร์เนชั่นแนล ทาวเวอร์ ชั้นที่ 16 หมู่ที่ 4 ถนนแจ้งวัฒนะ ตำบลปากเกร็ด อำเภอปากเกร็ด จ.นนทบุรี 11120",
        "ชื่อบริษัทภาษาอังกฤษ": "MONO TECHNOLOGY CO.,LTD.",
        "ชื่อบริษัทภาษาไทย": "บริษัท โมโน เทคโนโลยี จำกัด",
        "ข้อมูลสำหรับการติดต่อ": false,
        "ที่มา": "https://www.dataforthai.com/company/0105545029604/"
    },
    {
        "เลขทะเบียน": "0105558075871",
        "ประกอบธุรกิจ": "ประกอบกิจการผลิตรายการโทรทัศน์ ทั้งที่เกี่ยวข้องกับการแสดงและไม่เกี่ยวข้อง",
        "หมวดธุรกิจ": "กิจกรรมการผลิตรายการโทรทัศน์",
        "สถานะ": "ยังดำเนินกิจการอยู่",
        "วันที่จดทะเบียน": "7 พฤษภาคม 2558",
        "ทุนจดทะเบียน": "100,000,000 บาท",
        "สมัครงาน / ดูตำแหน่งงานว่าง": "ดูตำแหน่งงานจาก JOBTHAI",
        "ก่อตั้งโดย": "กรรมการ: นายบุญยงค์ ยงเจริญรัฐ, นายฉวนหู ชูว",
        "ที่ตั้ง": "92/1 ถนนนราธิวาสราชนครินทร์ แขวงช่องนนทรี เขตยานนาวา กรุงเทพมหานคร 10120",
        "ชื่อบริษัทภาษาอังกฤษ": "THAI-CHINA CULTURE AND MEDIA GROUP COMPANY LIMITED",
        "ชื่อบริษัทภาษาไทย": "บริษัท ไทย-จีน วัฒนธรรม แอนด์ มีเดีย กรุ๊ป จำกัด",
        "ข้อมูลสำหรับการติดต่อ": false,
        "ที่มา": "https://www.dataforthai.com/company/0105558075871/"
    },
    {
        "เลขทะเบียน": "0105559161551",
        "ประกอบธุรกิจ": "",
        "สถานะ": "ยังดำเนินกิจการอยู่",
        "วันที่จดทะเบียน": "12 ตุลาคม 2559",
        "ทุนจดทะเบียน": "115,500,000 บาท",
        "ก่อตั้งโดย": "กรรมการ: นายวู ซอง ซัง, นายซอง อู โจ, นายจัง โฮ ซอ, นางสาวเจฮยอน คิม, นางสาวอารี อารีจิตเสถียร, นายณรงค์ เจียรวนนท์, นายพีรธน เกษมศรี ณ อยุธยา, นางสาวยุภา ลีวงศ์เจริญ, นายซอง ฮุน จอง",
        "ที่ตั้ง": "18 อาคารทรู ทาวเวอร์ ถนนรัชดาภิเษก แขวงห้วยขวาง เขตห้วยขวาง กรุงเทพมหานคร 10310",
        "หมวดธุรกิจ": "กิจกรรมการผลิตรายการโทรทัศน์",
        "ชื่อบริษัทภาษาอังกฤษ": "TRUE CJ CREATIONS COMPANY LIMITED",
        "ชื่อบริษัทภาษาไทย": "บริษัท ทรู ซีเจ ครีเอชั่นส์ จำกัด",
        "ข้อมูลสำหรับการติดต่อ": false,
        "ที่มา": "https://www.dataforthai.com/company/0105559161551/"
    },
    {
        "เลขทะเบียน": "0135544003822",
        "ประกอบธุรกิจ": "ผลิตรายการโทรทัศน์ สื่อสิ่งพิมพ์ นิตยสาร และหนังสือ",
        "หมวดธุรกิจ": "กิจกรรมการผลิตรายการโทรทัศน์",
        "สถานะ": "ยังดำเนินกิจการอยู่",
        "วันที่จดทะเบียน": "19 กันยายน 2544",
        "ทุนจดทะเบียน": "120,000,000 บาท",
        "เว็บไซต์": "www.smartsme.tv",
        "ก่อตั้งโดย": "กรรมการ: นายธนพันธ์ วงศ์ชินศรี, นางสาวณรินณ์ทิพ วิริยะบัณฑิตกุล, นายวิเชฐ ตันติวานิช, นายโอฬาร วีระนนท์, นายธนา ทุมมานนท์, นางสาววิมลณ์เกศ สุวพัฒน์ธุนากร",
        "ที่ตั้ง": "47,49 ซอยลาดพร้าว 140 ถนนลาดพร้าว แขวงคลองจั่น เขตบางกะปิ กรุงเทพมหานคร 10240",
        "ชื่อบริษัทภาษาอังกฤษ": "PEOPLE MEDIA CO.,LTD.",
        "ชื่อบริษัทภาษาไทย": "บริษัท พีเอ็มจี คอร์ปอเรชั่น จำกัด",
        "ข้อมูลสำหรับการติดต่อ": true,
        "ที่มา": "https://www.dataforthai.com/company/0135544003822/"
    },
    {
        "เลขทะเบียน": "0105536002162",
        "ประกอบธุรกิจ": "ผลิตและจัดรายการโทรทัศน์",
        "หมวดธุรกิจ": "กิจกรรมการผลิตรายการโทรทัศน์",
        "สถานะ": "แปรสภาพ เป็น บริษัท คิง เจน จำกัด (มหาชน)",
        "วันที่จดทะเบียน": "8 มกราคม 2536",
        "ทุนจดทะเบียน": "120,000,000 บาท",
        "ที่ตั้ง": "1854 ถนนบางนา-ตราด แขวงบางนา เขตบางนา กรุงเทพมหานคร",
        "ชื่อบริษัทภาษาอังกฤษ": "NATION BROADCASTING CORPORATION LIMITED",
        "ชื่อบริษัทภาษาไทย": "บริษัท เนชั่น บรอดแคสติ้ง คอร์ปอเรชั่น จำกัด",
        "ข้อมูลสำหรับการติดต่อ": false,
        "ที่มา": "https://www.dataforthai.com/company/0105536002162/"
    },
    {
        "เลขทะเบียน": "0105547051615",
        "ประกอบธุรกิจ": "ผลิตและรับจ้างผลิตรายการทางวิทยุ,โทรทัศน์,แถบบันทึกภาพ,แถบบันทึกเสียงผลิตละครเวที",
        "หมวดธุรกิจ": "กิจกรรมการผลิตรายการโทรทัศน์",
        "สถานะ": "ยังดำเนินกิจการอยู่",
        "วันที่จดทะเบียน": "9 เมษายน 2547",
        "ทุนจดทะเบียน": "140,000,000 บาท",
        "สมัครงาน / ดูตำแหน่งงานว่าง": "ดูตำแหน่งงานจาก JOBTHAI",
        "ก่อตั้งโดย": "กรรมการ: นายถกลเกียรติ วีรวรรณ, นางกณิการ์ วีรวรรณ, นางสาวบุษบา ดาวเรือง, นางสมศรี พฤทธิพันธุ์, นายนิพนธ์ ผิวเณร, นายสิริชัย ตันติพงศ์อนันต์, นางสาวสุธาสินี บุศราพันธ์, นายศศวัต บุษยพันธ์, นางจิราภรณ์ รุ่งศรีทอง",
        "ที่ตั้ง": "99 ถนนรัชดาภิเษก แขวงดินแดง เขตดินแดง กรุงเทพมหานคร 10400",
        "ชื่อบริษัทภาษาอังกฤษ": "SCENARIO  COMPANY LIMITED",
        "ชื่อบริษัทภาษาไทย": "บริษัท ซีเนริโอ จำกัด",
        "ข้อมูลสำหรับการติดต่อ": false,
        "ที่มา": "https://www.dataforthai.com/company/0105547051615/"
    },
    {
        "เลขทะเบียน": "0105535159629",
        "ประกอบธุรกิจ": "ผลิตรายการโทรทัศน์และรายการบันเทิงรวมทั้งให้บริการโฆษณา",
        "หมวดธุรกิจ": "กิจกรรมการผลิตรายการโทรทัศน์",
        "สถานะ": "แปรสภาพ เป็น บริษัท ทีวี ธันเดอร์ จำกัด (มหาชน)",
        "วันที่จดทะเบียน": "30 พฤศจิกายน 2535",
        "ทุนจดทะเบียน": "150,000,000 บาท",
        "เว็บไซต์": "www.tvthunder.co.th",
        "ที่ตั้ง": "1213/309-310 ซอยลาดพร้าว 94 (ปัญจมิตร) ถนนศรีวรา แขวงพลับพลา เขตวังทองหลาง กรุงเทพมหานคร 10310",
        "ชื่อบริษัทภาษาอังกฤษ": "TV THUNDER COMPANY LIMITED",
        "ชื่อบริษัทภาษาไทย": "บริษัท ทีวี ธันเดอร์ จำกัด",
        "ข้อมูลสำหรับการติดต่อ": false,
        "ที่มา": "https://www.dataforthai.com/company/0105535159629/"
    },
    {
        "เลขทะเบียน": "0105555178467",
        "ประกอบธุรกิจ": "ผลิตรายการโทรทัศน์และจำหน่ายเวลาโฆษณา",
        "หมวดธุรกิจ": "กิจกรรมการผลิตรายการโทรทัศน์",
        "สถานะ": "ยังดำเนินกิจการอยู่",
        "วันที่จดทะเบียน": "4 ธันวาคม 2555",
        "ทุนจดทะเบียน": "150,000,000 บาท",
        "ก่อตั้งโดย": "กรรมการ: นางเยาวลักษณ์ พูลทอง, นางสาวสุภาพรรณ วิสฤตาภา, นางสาวนฤดี แซ่โค้ว",
        "ที่ตั้ง": "998/3 ชั้น 4 ถนนพหลโยธิน แขวงจอมพล เขตจตุจักร กรุงเทพมหานคร 10900",
        "ชื่อบริษัทภาษาอังกฤษ": "MEDIA SCENE COMPANY LIMITED",
        "ชื่อบริษัทภาษาไทย": "บริษัท มีเดีย ซีน จำกัด",
        "ข้อมูลสำหรับการติดต่อ": true,
        "ที่มา": "https://www.dataforthai.com/company/0105555178467/"
    },
    {
        "เลขทะเบียน": "0105539129414",
        "ประกอบธุรกิจ": "ผลิตรายการ รับจ้างโฆษณา รับเป็นที่ปรึกษาจัดการเกี่ยวกับกิจการบันเทิง",
        "หมวดธุรกิจ": "กิจกรรมการผลิตรายการโทรทัศน์",
        "สถานะ": "ยังดำเนินกิจการอยู่",
        "วันที่จดทะเบียน": "22 พฤศจิกายน 2539",
        "ทุนจดทะเบียน": "152,000,000 บาท",
        "ก่อตั้งโดย": "กรรมการ: นางจำนรรค์ ศิริตัน, นางลาวัลย์ กันชาติ, นายอารักษ์ คคะนาท",
        "ที่ตั้ง": "154 ซอยลาดพร้าว 107 ถนนลาดพร้าว แขวงคลองจั่น เขตบางกะปิ กรุงเทพมหานคร 10240",
        "ชื่อบริษัทภาษาอังกฤษ": "J S L HOLDING CO., LTD.",
        "ชื่อบริษัทภาษาไทย": "บริษัท เจ เอส แอล โกลบอล มีเดีย จำกัด",
        "ข้อมูลสำหรับการติดต่อ": true,
        "ที่มา": "https://www.dataforthai.com/company/0105539129414/"
    },
    {
        "เลขทะเบียน": "0105550055952",
        "ประกอบธุรกิจ": "การผลิตรายการโทรทัศน์ และรายการบันเทิง",
        "หมวดธุรกิจ": "กิจกรรมการผลิตรายการโทรทัศน์",
        "สถานะ": "ยังดำเนินกิจการอยู่",
        "วันที่จดทะเบียน": "29 พฤษภาคม 2550",
        "ทุนจดทะเบียน": "154,000,000 บาท",
        "ก่อตั้งโดย": "กรรมการ: นางสาวอุษณา มหากิจศิริ, นายอติเทพ ชดช้อย, นายเฉลิมชัย มหากิจศิริ",
        "ที่ตั้ง": "60/1 อาคารมนริริน (อาคาร เอ) ชั้นที่ 3 ห้องเลขที่ เอ 305 ซอยสายลม ถนนพหลโยธิน แขวงสามเสนใน เขตพญาไท กรุงเทพมหานคร 10400",
        "ชื่อบริษัทภาษาอังกฤษ": "FOUR- ONE-ENTERTAINMENT CO.,LTD.",
        "ชื่อบริษัทภาษาไทย": "บริษัท โฟร์ วัน วัน เอ็นเตอร์เทนเม้นท์ จำกัด",
        "ข้อมูลสำหรับการติดต่อ": false,
        "ที่มา": "https://www.dataforthai.com/company/0105550055952/"
    },
    {
        "เลขทะเบียน": "0105550100974",
        "ประกอบธุรกิจ": "การขายส่งแร่โลหะที่เป็นเหล็กและนอกกลุ่มเหล็ก",
        "หมวดธุรกิจ": "การขายส่งของเสียและเศษวัสดุเพื่อนำกลับมาใช้ใหม่",
        "สถานะ": "ยังดำเนินกิจการอยู่",
        "วันที่จดทะเบียน": "25 กันยายน 2550",
        "ทุนจดทะเบียน": "832,780,000 บาท",
        "ก่อตั้งโดย": "กรรมการ: นางสาวสุทธิดา ลีสวัสดิ์ตระกูล, นายศุภมงคล มาโนช, นายโยธิน ชาวปากน้ำ",
        "ที่ตั้ง": "339 หมู่ที่ 6 ถนนปากร่วม-อ่าวอุดม ตำบลบ่อวิน อำเภอศรีราชา จ.ชลบุรี 20230",
        "ชื่อบริษัทภาษาอังกฤษ": "WASTECH ESG COMPANY LIMITED",
        "ชื่อบริษัทภาษาไทย": "บริษัท เวสท์เทค อีเอสจี จำกัด",
        "ข้อมูลสำหรับการติดต่อ": false,
        "ที่มา": "https://www.dataforthai.com/company/0105550100974/"
    },
    {
        "เลขทะเบียน": "0105561076565",
        "ประกอบธุรกิจ": "ผลิตรายการโทรทัศน์",
        "หมวดธุรกิจ": "กิจกรรมการผลิตรายการโทรทัศน์",
        "สถานะ": "ยังดำเนินกิจการอยู่",
        "วันที่จดทะเบียน": "3 พฤษภาคม 2561",
        "ทุนจดทะเบียน": "200,000,000 บาท",
        "ก่อตั้งโดย": "กรรมการ: นายจอนนี่ แอนโฟเน, นายณัฐพล พวงเพชร",
        "ที่ตั้ง": "1090, 1092 ถนนศรีนครินทร์ แขวงพัฒนาการ เขตสวนหลวง กรุงเทพมหานคร 10250",
        "ชื่อบริษัทภาษาอังกฤษ": "MAXIMUS LEADER CO., LTD.",
        "ชื่อบริษัทภาษาไทย": "บริษัท แม็กซิมัส ลีดเดอร์ จำกัด",
        "ข้อมูลสำหรับการติดต่อ": false,
        "ที่มา": "https://www.dataforthai.com/company/0105561076565/"
    },
    {
        "เลขทะเบียน": "0105548092757",
        "ประกอบธุรกิจ": "ผลิตรายการโทรทัศน์ผ่านดาวเทียม,บริการโฆษณาและประชาสัมพันธ์",
        "หมวดธุรกิจ": "กิจกรรมการผลิตรายการโทรทัศน์",
        "สถานะ": "ยังดำเนินกิจการอยู่",
        "วันที่จดทะเบียน": "15 กรกฎาคม 2548",
        "ทุนจดทะเบียน": "200,000,000 บาท",
        "ก่อตั้งโดย": "กรรมการ: นางสาวบุษบา ดาวเรือง, นายภาวิต จิตรกร, นายสมภพ บุษปวนิช, นายกิตติศักดิ์ ช่วงอรุณ",
        "ที่ตั้ง": "50 ถนนสุขุมวิท 21 (อโศก) แขวงคลองเตยเหนือ เขตวัฒนา กรุงเทพมหานคร 10110",
        "ชื่อบริษัทภาษาอังกฤษ": "FANTV COMPANY LIMITED",
        "ชื่อบริษัทภาษาไทย": "บริษัท แฟนทีวี จำกัด",
        "ข้อมูลสำหรับการติดต่อ": false,
        "ที่มา": "https://www.dataforthai.com/company/0105548092757/"
    },
    {
        "หลักทรัพย์": "TVT",
        "ประกอบธุรกิจ": "จัดการ ส่งเสริมและผลิตการแสดงและดนตรี ละครและภาพยนตร์ทุกชนิด",
        "สถานะ": "ยังดำเนินกิจการอยู่",
        "จดทะเบียน": "2 ธันวาคม 2557   แปรสภาพจาก บริษัท ทีวี ธันเดอร์ จำกัด",
        "ทุนจดทะเบียน": "250,000,000 บาท",
        "ก่อตั้งโดย": "กรรมการ: นายสมพงษ์ วรรณภิญโญ, นางภัทรภร วรรณภิญโญ, นายภูษิต ไล้ทอง, นายพิรัฐ เย็นสุดใจ, นายณฐกฤต วรรณภิญโญ, นายมนตรี โสคติยานุรักษ์, นางกัลยานี ภาคอัต, นายสุพงษ์ ลิ้มธนากุล",
        "ที่ตั้ง": "1213/309-310 ซอยลาดพร้าว 94 (ปัญจมิตร) ถนนศรีวรา แขวงพลับพลา เขตวังทองหลาง กรุงเทพมหานคร 10310",
        "หมวดธุรกิจ": "กิจกรรมการผลิตรายการโทรทัศน์",
        "ชื่อบริษัทภาษาอังกฤษ": "",
        "ชื่อบริษัทภาษาไทย": "บริษัท ทีวี ธันเดอร์ จำกัด (มหาชน)",
        "ข้อมูลสำหรับการติดต่อ": true,
        "ที่มา": "https://www.dataforthai.com/company/0107557000446/",
        "เลขทะเบียน": "0107557000446"
    },
    {
        "เลขทะเบียน": "0107546000075",
        "ประกอบธุรกิจ": "ขายโฆษณารายการโทรทัศน์จัดคอนเสิร์ตและการแสดง",
        "หมวดธุรกิจ": "กิจกรรมการผลิตรายการโทรทัศน์",
        "สถานะ": "ยังดำเนินกิจการอยู่",
        "วันที่จดทะเบียน": "12 มีนาคม 2546",
        "ทุนจดทะเบียน": "250,000,000 บาท",
        "เว็บไซต์": "www.qikplay.com",
        "ก่อตั้งโดย": "กรรมการ: นายไบรอันลินด์เซ มาร์การ์, นายประวิทย์ จิตนราพงศ์, นายเนล เวนน์ ทอมบ์สัน, นายคมกริช ศิริรัตน์, นายโชคชัย เอี่ยมฤทธิไกร",
        "ที่ตั้ง": "998/3 อาคาร7 ชั้นที่ 4-5,7 ถนนพหลโยธิน แขวงจอมพล เขตจตุจักร กรุงเทพมหานคร 10900",
        "ชื่อบริษัทภาษาอังกฤษ": "TERO ENTERTAINMENT PUBLIC COMPANY LIMITED",
        "ชื่อบริษัทภาษาไทย": "บริษัท เทโร เอ็นเทอร์เทนเม้นท์ จำกัด (มหาชน)",
        "ข้อมูลสำหรับการติดต่อ": true,
        "ที่มา": "https://www.dataforthai.com/company/0107546000075/"
    },
    {
        "เลขทะเบียน": "0125535002843",
        "ประกอบธุรกิจ": "",
        "สถานะ": "ยังดำเนินกิจการอยู่",
        "วันที่จดทะเบียน": "27 พฤษภาคม 2535",
        "ทุนจดทะเบียน": "270,000,000 บาท",
        "ก่อตั้งโดย": "กรรมการ: นายวินัย วีระภุชงค์, นายสุภชัย วีระภุชงค์, นางสาวทิพย์วรรณ วีระภุชงค์, นายวโรดม วีระภุชงค์",
        "ที่ตั้ง": "14 ซอยงามวงศ์วาน 8 ถนนงามวงศ์วาน ตำบลบางเขน อำเภอเมืองนนทบุรี จ.นนทบุรี 11000",
        "หมวดธุรกิจ": "การผลิตเครื่องรับโทรทัศน์",
        "ชื่อบริษัทภาษาอังกฤษ": "MICA MEDIA COMPANY LIMITED",
        "ชื่อบริษัทภาษาไทย": "บริษัท มิกา มีเดีย จำกัด",
        "ข้อมูลสำหรับการติดต่อ": false,
        "ที่มา": "https://www.dataforthai.com/company/0125535002843/"
    },
    {
        "เลขทะเบียน": "0105544101948",
        "ประกอบธุรกิจ": "ธุรกิจสื่อ",
        "หมวดธุรกิจ": "กิจกรรมการผลิตรายการโทรทัศน์",
        "สถานะ": "ยังดำเนินกิจการอยู่",
        "วันที่จดทะเบียน": "18 ตุลาคม 2544",
        "ทุนจดทะเบียน": "300,000,000 บาท",
        "เว็บไซต์": "www.facebook.com/dgshoppingofficial",
        "ก่อตั้งโดย": "กรรมการ: นายสุพรรณ เสือหาญ, นางสาวนงลักษณ์ งามโรจน์",
        "ที่ตั้ง": "27 อาคารอาร์เอสกรุ๊ป ทาวเวอร์ บี ชั้น 3 ถนนประเสริฐมนูกิจ แขวงเสนานิคม เขตจตุจักร กรุงเทพมหานคร 10900",
        "ชื่อบริษัทภาษาอังกฤษ": "RS MULTIMEDIA CO., LTD.",
        "ชื่อบริษัทภาษาไทย": "บริษัท อาร์เอส มัลติมีเดีย จำกัด",
        "ข้อมูลสำหรับการติดต่อ": true,
        "ที่มา": "https://www.dataforthai.com/company/0105544101948/"
    },
    {
        "เลขทะเบียน": "0105557184863",
        "ประกอบธุรกิจ": "ซื้อขาย จำหน่ายผลิตภัณฑ์รายการทางโทรทัศน์ ภาพยนตร์ สารคดี",
        "หมวดธุรกิจ": "กิจกรรมการผลิตรายการโทรทัศน์",
        "สถานะ": "แปรสภาพ เป็น บริษัท ไฟเบอร์วัน จำกัด (มหาชน)",
        "วันที่จดทะเบียน": "18 ธันวาคม 2557",
        "ทุนจดทะเบียน": "350,000,000 บาท",
        "ที่ตั้ง": "89 อาคารเอไอเอ แคปปิตอล เซนเตอร์ ชั้น 15 ถนนรัชดาภิเษก แขวงดินแดง เขตดินแดง กรุงเทพมหานคร 10400",
        "ชื่อบริษัทภาษาอังกฤษ": "FIBERONE COMPANY LIMITED",
        "ชื่อบริษัทภาษาไทย": "บริษัท ไฟเบอร์วัน จำกัด",
        "ข้อมูลสำหรับการติดต่อ": true,
        "ที่มา": "https://www.dataforthai.com/company/0105557184863/"
    },
    {
        "สถานะ": "ยังดำเนินกิจการอยู่",
        "จดทะเบียน": "2 มีนาคม 2544",
        "ทุนจดทะเบียน": "452,500,000 บาท",
        "ก่อตั้งโดย": "กรรมการ: นายสุรชัย เชษฐโชติศักดิ์, นางพรพรรณ เตชรุ่งชัยกุล, นางสาวนิภา บัญญัติเจริญ",
        "ที่ตั้ง": "27 อาคารอาร์เอสกรุ๊ป ทาวเวอร์ เอ ชั้น 3,7 ถนนประเสริฐมนูกิจ แขวงเสนานิคม เขตจตุจักร กรุงเทพมหานคร 10900",
        "หมวดธุรกิจ": "การขายตรง",
        "ประกอบธุรกิจ": "",
        "ชื่อบริษัทภาษาอังกฤษ": "RS CONNECT CO., LTD.",
        "ชื่อบริษัทภาษาไทย": "บริษัท อาร์เอส คอนเน็ค จำกัด",
        "ข้อมูลสำหรับการติดต่อ": true,
        "ที่มา": "https://www.dataforthai.com/company/0105544021316/",
        "เลขทะเบียน": "0105544021316"
    },
    {
        "เลขทะเบียน": "0105534087802",
        "ประกอบธุรกิจ": "ผลิตรายการโทรทัศน์และจำหน่ายเวลาโฆษณา ผลิตละคร",
        "หมวดธุรกิจ": "กิจกรรมการผลิตรายการโทรทัศน์",
        "สถานะ": "ยังดำเนินกิจการอยู่",
        "วันที่จดทะเบียน": "16 กันยายน 2534",
        "ทุนจดทะเบียน": "491,100,000 บาท",
        "เว็บไซต์": "http://mediastudio.co.th/",
        "ก่อตั้งโดย": "กรรมการ: นายสรรสฤษดิ์ เย็นบำรุง, นายภูมิชาย วัชรพงศ์, นางเยาวลักษณ์ พูลทอง, นางสาวสุภาพรรณ วิสฤตาภา",
        "ที่ตั้ง": "998/3 ชั้น 3 ถึงชั้น 4 ถนนพหลโยธิน แขวงจอมพล เขตจตุจักร กรุงเทพมหานคร 10900",
        "ชื่อบริษัทภาษาอังกฤษ": "MEDIA STUDIO CO., LTD.",
        "ชื่อบริษัทภาษาไทย": "บริษัท มีเดีย สตูดิโอ จำกัด",
        "ข้อมูลสำหรับการติดต่อ": true,
        "ที่มา": "https://www.dataforthai.com/company/0105534087802/"
    },
    {
        "เลขทะเบียน": "0105549043181",
        "ประกอบธุรกิจ": "ประกอบกิจการให้กู้ยืมเงินทั้งแบบมีและไม่มีหลักทรัพย์ค้ำประกัน",
        "หมวดธุรกิจ": "การให้สินเชื่ออื่นๆซึ่งมิได้จัดประเภทไว้ในที่อื่น",
        "สถานะ": "ยังดำเนินกิจการอยู่",
        "วันที่จดทะเบียน": "30 มีนาคม 2549",
        "ทุนจดทะเบียน": "500,000,000 บาท",
        "ก่อตั้งโดย": "กรรมการ: นางสาวปรมาภรณ์ ปราสาททองโอสถ, นายตนุพล วิรุฬหการุญ, นางสาวฐานันดร์ บรรจงดี, นางสาวเฉลิมวรรณ วินัยชาติศักดิ์",
        "ที่ตั้ง": "9/25 ซอยโชคชัยร่วมมิตร แขวงจอมพล เขตจตุจักร กรุงเทพมหานคร 10900",
        "ชื่อบริษัทภาษาอังกฤษ": "PRANANPORN COMPANY LIMTED",
        "ชื่อบริษัทภาษาไทย": "บริษัท ประนันท์ภรณ์ จำกัด",
        "ข้อมูลสำหรับการติดต่อ": false,
        "ที่มา": "https://www.dataforthai.com/company/0105549043181/"
    },
    {
        "สถานะ": "ยังดำเนินกิจการอยู่",
        "จดทะเบียน": "11 ตุลาคม 2545",
        "ทุนจดทะเบียน": "591,420,000 บาท",
        "ก่อตั้งโดย": "กรรมการ: นายชยานนท์ อุลิศ, นายภูมิชาย วัชรพงศ์, นายกมล รัตนไชย, นางลดาวัลย์ คุ้มทรัพย์, นายชนินทร อุลิศ",
        "ที่ตั้ง": "305/12 ซอยสุโขทัย 6 ถนนสุโขทัย แขวงดุสิต เขตดุสิต กรุงเทพมหานคร 10300",
        "หมวดธุรกิจ": "กิจกรรมการผลิตรายการโทรทัศน์",
        "ประกอบธุรกิจ": "",
        "ชื่อบริษัทภาษาอังกฤษ": "THE STUDIO PARK (THAILAND) COMPANY LIMITED",
        "ชื่อบริษัทภาษาไทย": "บริษัท เดอะ สตูดิโอ พาร์ค (ประเทศไทย) จำกัด",
        "ข้อมูลสำหรับการติดต่อ": false,
        "ที่มา": "https://www.dataforthai.com/company/0105545108326/",
        "เลขทะเบียน": "0105545108326"
    },
    {
        "เลขทะเบียน": "0107545000365",
        "หลักทรัพย์": "MATCH",
        "ประกอบธุรกิจ": "การจัดรายการโทรทัศน์รับจ้างผลิตสื่อประชาสัมพันธ์",
        "หมวดธุรกิจ": "กิจกรรมการผลิตรายการโทรทัศน์",
        "สถานะ": "ยังดำเนินกิจการอยู่",
        "วันที่จดทะเบียน": "19 พฤศจิกายน 2545",
        "ทุนจดทะเบียน": "781,629,851 บาท",
        "เว็บไซต์": "http://www.matchinggroup.com",
        "ก่อตั้งโดย": "กรรมการ: นายสรรสฤษดิ์ เย็นบำรุง, นายภูมิชาย วัชรพงศ์, นายคมกริช ศิริรัตน์, นายอัครรัตน์ ณ ระนอง, นายฉัตรพี ตันติเฉลิม, นายกมล รัตนไชย, นางเยาวลักษณ์ พูลทอง, นายชยานนท์ อุลิศ, นายเนล เวนน์ ทอมบ์สัน",
        "ที่ตั้ง": "305/12 ซอยสุโขทัย 6 ถนนสุโขทัย แขวงดุสิต เขตดุสิต กรุงเทพมหานคร 10300",
        "ชื่อบริษัทภาษาอังกฤษ": "MATCHING MAXIMIZE SOLUTION PUBLIC COMPANY LIMITED",
        "ชื่อบริษัทภาษาไทย": "บริษัท แม็ทชิ่ง แม็กซิไมซ์ โซลูชั่น จำกัด (มหาชน)",
        "ข้อมูลสำหรับการติดต่อ": true,
        "ที่มา": "https://www.dataforthai.com/company/0107545000365/"
    },
    {
        "เลขทะเบียน": "0105552050184",
        "ประกอบธุรกิจ": "การผลิตรายการโทรทัศน์และให้บริการโฆษณาผ่านสื่อโทรทัศน์ สื่อดิจิตอล",
        "หมวดธุรกิจ": "กิจกรรมการผลิตรายการโทรทัศน์",
        "สถานะ": "ยังดำเนินกิจการอยู่",
        "วันที่จดทะเบียน": "25 พฤษภาคม 2552",
        "ทุนจดทะเบียน": "800,000,000 บาท",
        "สมัครงาน / ดูตำแหน่งงานว่าง": "ดูตำแหน่งงานจาก JOBTHAI",
        "ก่อตั้งโดย": "กรรมการ: นางพันธุ์ทิพา ศกุณต์ไชย",
        "ที่ตั้ง": "303 ซอยลาดพร้าว 101 (วัดบึงทองหลาง) แขวงคลองเจ้าคุณสิงห์ เขตวังทองหลาง กรุงเทพมหานคร 10310",
        "ชื่อบริษัทภาษาอังกฤษ": "THAITV COMPANY LIMITED",
        "ชื่อบริษัทภาษาไทย": "บริษัท ไทยทีวี จำกัด",
        "ข้อมูลสำหรับการติดต่อ": false,
        "ที่มา": "https://www.dataforthai.com/company/0105552050184/"
    },
    {
        "เลขทะเบียน": "0105555177371",
        "ประกอบธุรกิจ": "ผลิตรายการโทรทัศน์และให้บริการโฆษณาผ่านสื่อโทรทัศน์",
        "หมวดธุรกิจ": "กิจกรรมการผลิตรายการโทรทัศน์",
        "สถานะ": "ยังดำเนินกิจการอยู่",
        "วันที่จดทะเบียน": "30 พฤศจิกายน 2555",
        "ทุนจดทะเบียน": "1,070,000,000 บาท",
        "ก่อตั้งโดย": "กรรมการ: นายฉาย บุนนาค, นางวรางคณา กัลยาณประดิษฐ, นายสมชาย มีเสน",
        "ที่ตั้ง": "1854 ชั้น 5 ถนนเทพรัตน แขวงบางนาใต้ เขตบางนา กรุงเทพมหานคร 10260",
        "ชื่อบริษัทภาษาอังกฤษ": "NATION TV CO., LTD.",
        "ชื่อบริษัทภาษาไทย": "บริษัท เนชั่น ทีวี จำกัด",
        "ข้อมูลสำหรับการติดต่อ": false,
        "ที่มา": "https://www.dataforthai.com/company/0105555177371/"
    },
    {
        "เลขทะเบียน": "0107552000103",
        "หลักทรัพย์": "KGEN",
        "ประกอบธุรกิจ": "การบริการให้คำปรึกษาด้านการบริหารจัดการ",
        "หมวดธุรกิจ": "กิจกรรมให้คำปรึกษาด้านการบริหารจัดการอื่นๆซึ่งมิได้จัด ประเภทไว้ในที่อื่น",
        "สถานะ": "ยังดำเนินกิจการอยู่",
        "วันที่จดทะเบียน": "4 พฤษภาคม 2552",
        "ทุนจดทะเบียน": "1,700,580,555 บาท",
        "เว็บไซต์": "www.kinggen.co.th",
        "ก่อตั้งโดย": "กรรมการ: นายสามารถ ดีพิจารณ์, นางสาวพรทิพย์ ตรงกิ่งตอน, นายอรรถยุต วุฒิธรรมมี, นางสาวพรรณพิมล โกมลภิส, นายธีร เจียศิริพงษ์กุล, นายสรไกร ศรีสัจจารักษ์, นายอภิชาติ เพียรเจริญ, นายบุญรัตน์ วิญญุกานนท์, นายจิระเดช ห้วยหงษ์ทอง",
        "ที่ตั้ง": "194 ถนนเสรีไทย แขวงคันนายาว เขตคันนายาว กรุงเทพมหานคร 10230",
        "ชื่อบริษัทภาษาอังกฤษ": "KING GEN PUBLIC COMPANY LIMITED",
        "ชื่อบริษัทภาษาไทย": "บริษัท คิง เจน จำกัด (มหาชน)",
        "ข้อมูลสำหรับการติดต่อ": true,
        "ที่มา": "https://www.dataforthai.com/company/0107552000103/"
    },
    {
        "เลขทะเบียน": "0107538000673",
        "หลักทรัพย์": "BEC",
        "ประกอบธุรกิจ": "",
        "สถานะ": "ยังดำเนินกิจการอยู่",
        "วันที่จดทะเบียน": "23 พฤศจิกายน 2538",
        "ทุนจดทะเบียน": "2,000,000,000 บาท",
        "เว็บไซต์": "www.becworld.com",
        "สมัครงาน / ดูตำแหน่งงานว่าง": "ดูตำแหน่งงานจาก JOBSDB",
        "ก่อตั้งโดย": "กรรมการ: นายสมชัย บุญนำศิริ, นายสมประสงค์ บุญยะชัย, นางสาวรัตนา มาลีนนท์, นางสาวนิภา มาลีนนท์, นางสาวอัมพร มาลีนนท์, นางรัชนี นิพัทธกุศล, นายประธาน รังสิมาภรณ์, นายมานิต บุญประกอบ, นายชาญศักดิ์ เฟื่องฟู, นายแมทธิว กิจโอธาน, นางสาวเทรซีแอนน์ มาลีนนท์, นายธัชพล โปษยานนท์, นางสาวปิยวดี มาลีนนท์",
        "ที่ตั้ง": "3199 อาคารมาลีนนท์ ทาวเวอร์ ชั้นที่ 2, 3, 4, 9, 10, 30-34 ถนนพระราม 4 แขวงคลองตัน เขตคลองเตย กรุงเทพมหานคร 10110",
        "หมวดธุรกิจ": "กิจกรรมการผลิตรายการโทรทัศน์",
        "ชื่อบริษัทภาษาอังกฤษ": "BEC WORLD PUBLIC COMPANY LIMITED",
        "ชื่อบริษัทภาษาไทย": "บริษัท บีอีซี เวิลด์ จำกัด (มหาชน)",
        "ข้อมูลสำหรับการติดต่อ": true,
        "ที่มา": "https://www.dataforthai.com/company/0107538000673/"
    },
    {
        "เลขทะเบียน": "0105554108821",
        "ประกอบธุรกิจ": "สนับสนุนรายการโทรทัศน์โฆษณา",
        "หมวดธุรกิจ": "กิจกรรมการผลิตรายการโทรทัศน์",
        "สถานะ": "ยังดำเนินกิจการอยู่",
        "วันที่จดทะเบียน": "17 สิงหาคม 2554",
        "ทุนจดทะเบียน": "2,000,000,000 บาท",
        "ก่อตั้งโดย": "กรรมการ: นายสมพันธ์ จารุมิลินท, พลตำรวจเอกพรศักดิ์ ดุรงควิบูลย์, พลตำรวจเอกนพดล สมบูรณ์ทรัพย์, พลเอกนินนาท เบี้ยวไข่มุข, นายอภัยชนม์ วัชรสินธุ์, นายอัศวิน อ้วนโพธิ์กลาง, นายอภิศักดิ์ ธนเศรษฐกร, นางรุ่งฟ้า เกียรติพจน์, นายองอาจ ประภากมล, นางสาวนันทนี วงศ์อำนิษฐกุล",
        "ที่ตั้ง": "18 อาคารทรู ทาวเวอร์ ถนนรัชดาภิเษก แขวงห้วยขวาง เขตห้วยขวาง กรุงเทพมหานคร 10310",
        "ชื่อบริษัทภาษาอังกฤษ": "THAI NEWS NETWORK (INN) CO.,LTD.",
        "ชื่อบริษัทภาษาไทย": "บริษัท ไทย นิวส์ เน็ตเวิร์ค (ทีเอ็นเอ็น) จำกัด",
        "ข้อมูลสำหรับการติดต่อ": false,
        "ที่มา": "https://www.dataforthai.com/company/0105554108821/"
    },
    {
        "เลขทะเบียน": "0125556020913",
        "ประกอบธุรกิจ": "ผลิตรายการสื่อโทรทัศน์และสื่ออื่นๆ รวมทั้งให้บริการข้อมูลบันเทิง",
        "หมวดธุรกิจ": "กิจกรรมการผลิตรายการโทรทัศน์",
        "สถานะ": "ยังดำเนินกิจการอยู่",
        "วันที่จดทะเบียน": "9 กันยายน 2556",
        "ทุนจดทะเบียน": "2,490,000,000 บาท",
        "ก่อตั้งโดย": "กรรมการ: นายนวมินทร์ ประสพเนตร, นายบรรณสิทธิ์ รักวงษ์",
        "ที่ตั้ง": "29/9 หมู่ที่ 4 ถนนชัยพฤกษ์ ตำบลบางพลับ อำเภอปากเกร็ด จ.นนทบุรี 11120",
        "ชื่อบริษัทภาษาอังกฤษ": "MONO BROADCAST COMPANY LIMITED",
        "ชื่อบริษัทภาษาไทย": "บริษัท โมโน บรอดคาซท์ จำกัด",
        "ข้อมูลสำหรับการติดต่อ": false,
        "ที่มา": "https://www.dataforthai.com/company/0125556020913/"
    },
    {
        "ประกอบธุรกิจ": "ผลิตรายการเพื่อออกอากาศทั่วไป",
        "สถานะ": "ยังดำเนินกิจการอยู่",
        "จดทะเบียน": "9 ตุลาคม 2546",
        "ทุนจดทะเบียน": "577,500,000 บาท",
        "ก่อตั้งโดย": "กรรมการ: นายพานทองแท้ ชินวัตร, นายเฉลิม แผลงศร",
        "ที่ตั้ง": "414 ถนนพหลโยธิน แขวงสามเสนใน เขตพญาไท กรุงเทพมหานคร 10400",
        "หมวดธุรกิจ": "กิจกรรมการผลิตรายการโทรทัศน์",
        "ชื่อบริษัทภาษาอังกฤษ": "HOW COME ENTERTAINMENT  COMPANY LIMITED",
        "ชื่อบริษัทภาษาไทย": "บริษัท วอยซ์ ทีวี จำกัด",
        "ข้อมูลสำหรับการติดต่อ": false,
        "ที่มา": "https://www.dataforthai.com/company/0105546123311/",
        "เลขทะเบียน": "0105546123311"
    },
    {
        "เลขทะเบียน": "0125553016125",
        "ประกอบธุรกิจ": "ผลิตรายการสื่อโทรทัศน์และสื่ออื่นๆ รวมทั้งให้บริการข้อมูลบันเทิง",
        "หมวดธุรกิจ": "กิจกรรมการผลิตรายการโทรทัศน์",
        "สถานะ": "ยังดำเนินกิจการอยู่",
        "วันที่จดทะเบียน": "4 ตุลาคม 2553",
        "ทุนจดทะเบียน": "3,020,000,000 บาท",
        "เว็บไซต์": "mono.co.th",
        "ก่อตั้งโดย": "กรรมการ: นายนวมินทร์ ประสพเนตร, นายศิริ เหลืองสวัสดิ์, นายบรรณสิทธิ์ รักวงษ์",
        "ที่ตั้ง": "29/9 หมู่ที่ 4 ถนนชัยพฤกษ์ ตำบลบางพลับ อำเภอปากเกร็ด จ.นนทบุรี 11120",
        "ชื่อบริษัทภาษาอังกฤษ": "MONO PRODUCTION CO.,LTD.",
        "ชื่อบริษัทภาษาไทย": "บริษัท โมโน โปรดักชั่น จำกัด",
        "ข้อมูลสำหรับการติดต่อ": true,
        "ที่มา": "https://www.dataforthai.com/company/0125553016125/"
    },
    {
        "เลขทะเบียน": "0105556143594",
        "ประกอบธุรกิจ": "",
        "สถานะ": "ยังดำเนินกิจการอยู่",
        "วันที่จดทะเบียน": "6 กันยายน 2556",
        "ทุนจดทะเบียน": "3,205,000,000 บาท",
        "ก่อตั้งโดย": "กรรมการ: นายกิตติศักดิ์ ช่วงอรุณ, นายสันติสุข จงมั่นคง, นางวิภาพร สมคิด",
        "ที่ตั้ง": "50 อาคารจีเอ็มเอ็ม แกรมมี่ เพลส ถนนสุขุมวิท 21 (อโศก) แขวงคลองเตยเหนือ เขตวัฒนา กรุงเทพมหานคร 10110",
        "หมวดธุรกิจ": "กิจกรรมการผลิตรายการโทรทัศน์",
        "ชื่อบริษัทภาษาอังกฤษ": "GMM CHANNEL COMPANY LIMITED",
        "ชื่อบริษัทภาษาไทย": "บริษัท จีเอ็มเอ็ม แชนแนล จำกัด",
        "ข้อมูลสำหรับการติดต่อ": false,
        "ที่มา": "https://www.dataforthai.com/company/0105556143594/"
    },
    {
        "เลขทะเบียน": "0107564000146",
        "หลักทรัพย์": "ONEE",
        "ประกอบธุรกิจ": "",
        "สถานะ": "ยังดำเนินกิจการอยู่",
        "วันที่จดทะเบียน": "3 พฤษภาคม 2564",
        "ทุนจดทะเบียน": "4,762,500,000 บาท",
        "เว็บไซต์": "www.theoneenterprise.com",
        "ก่อตั้งโดย": "กรรมการ: นายไพบูลย์ ดำรงชัยธรรม, นางสาวอิงฟ้า ดำรงชัยธรรม, นายระฟ้า ดำรงชัยธรรม, นายถกลเกียรติ วีรวรรณ, นายปิยะ ซอโสตถิกุล, นางสาวจรรย์จิรา พนิตพล, นางสาวบุษบา ดาวเรือง, นางสาวสุวภา เจริญยิ่ง, นายศิโรตม์ เสตะพันธุ, นางดวงมณี สุขุม, นายครรชิต บุนะจินดา, นายนาฬิกอติภัค แสงสนิท, นางดวงใจ หล่อเลิศวิทย์",
        "ที่ตั้ง": "50 อาคารจีเอ็มเอ็ม แกรมมี่ เพลส ถนนสุขุมวิท 21 (อโศก) แขวงคลองเตยเหนือ เขตวัฒนา กรุงเทพมหานคร 10110",
        "หมวดธุรกิจ": "กิจกรรมของบริษัทโฮลดิ้งที่ลงทุนในธุรกิจการเงินเป็นหลัก",
        "ชื่อบริษัทภาษาอังกฤษ": "THE ONE ENTERPRISE PUBLIC COMPANY LIMITED",
        "ชื่อบริษัทภาษาไทย": "บริษัท เดอะ วัน เอ็นเตอร์ไพรส์ จำกัด (มหาชน)",
        "ข้อมูลสำหรับการติดต่อ": true,
        "ที่มา": "https://www.dataforthai.com/company/0107564000146/"
    }
]